{"images":[{"startdate":"20211116","fullstartdate":"202111160800","enddate":"20211117","url":"/th?id=OHR.HogwartsExpress_EN-US9194653227_1920x1080.jpg&rf=LaDigue_1920x1080.jpg&pid=hp","urlbase":"/th?id=OHR.HogwartsExpress_EN-US9194653227","copyright":"The Jacobite steam train crossing the Glenfinnan Viaduct in Inverness-shire, Scotland (© The Escape of Malee/Shutterstock)","copyrightlink":"https://www.bing.com/search?q=glenfinnan+viaduct&form=hpcapt&filters=HpDate%3a%2220211116_0800%22","title":"All aboard the Hogwarts Express","quiz":"/search?q=Bing+homepage+quiz&filters=WQOskey:%22HPQuiz_20211116_HogwartsExpress%22&FORM=HPQUIZ","wp":true,"hsh":"323812506ee408e674f00558c9c0063c","drk":1,"top":1,"bot":1,"hs":[]},{"startdate":"20211115","fullstartdate":"202111150800","enddate":"20211116","url":"/th?id=OHR.FloridaManatee_EN-US9136189368_1920x1080.jpg&rf=LaDigue_1920x1080.jpg&pid=hp","urlbase":"/th?id=OHR.FloridaManatee_EN-US9136189368","copyright":"Manatee in Florida (© Paul E Tessier/Cavan Images/Offset by Shutterstock)","copyrightlink":"https://www.bing.com/search?q=manatee&form=hpcapt&filters=HpDate%3a%2220211115_0800%22","title":"Spotlight on the 'sea cow'","quiz":"/search?q=Bing+homepage+quiz&filters=WQOskey:%22HPQuiz_20211115_FloridaManatee%22&FORM=HPQUIZ","wp":true,"hsh":"40b08fb754833f07e9851c62a98bf1d7","drk":1,"top":1,"bot":1,"hs":[]},{"startdate":"20211114","fullstartdate":"202111140800","enddate":"20211115","url":"/th?id=OHR.FirstCliff_EN-US9082558650_1920x1080.jpg&rf=LaDigue_1920x1080.jpg&pid=hp","urlbase":"/th?id=OHR.FirstCliff_EN-US9082558650","copyright":"First Cliff Walk on First near Grindelwald, Switzerland (© Hans-Georg Eiben/eStock Photo)","copyrightlink":"https://www.bing.com/search?q=First+Cliff+Walk+by+Tissot&form=hpcapt&filters=HpDate%3a%2220211114_0800%22","title":"Walking on air","quiz":"/search?q=Bing+homepage+quiz&filters=WQOskey:%22HPQuiz_20211114_FirstCliff%22&FORM=HPQUIZ","wp":true,"hsh":"60e69831afe56fe0a9da4bb128924fe5","drk":1,"top":1,"bot":1,"hs":[]},{"startdate":"20211113","fullstartdate":"202111130800","enddate":"20211114","url":"/th?id=OHR.ElTajo_EN-US9027914209_1920x1080.jpg&rf=LaDigue_1920x1080.jpg&pid=hp","urlbase":"/th?id=OHR.ElTajo_EN-US9027914209","copyright":"Aerial view of El Tajo gorge and the Puente Nuevo bridge in Ronda, Málaga, Spain (© Jude Newkirk/Amazing Aerial Agency)","copyrightlink":"https://www.bing.com/search?q=ronda+spain&form=hpcapt&filters=HpDate%3a%2220211113_0800%22","title":"A gorge-ous town divided","quiz":"/search?q=Bing+homepage+quiz&filters=WQOskey:%22HPQuiz_20211113_ElTajo%22&FORM=HPQUIZ","wp":true,"hsh":"a2cad820b3f1f5e13fb06ae156fd33c2","drk":1,"top":1,"bot":1,"hs":[]},{"startdate":"20211112","fullstartdate":"202111120800","enddate":"20211113","url":"/th?id=OHR.BeaversBend_EN-US8963318493_1920x1080.jpg&rf=LaDigue_1920x1080.jpg&pid=hp","urlbase":"/th?id=OHR.BeaversBend_EN-US8963318493","copyright":"Beavers Bend Resort Park near Broken Bow, Oklahoma (© Inge Johnsson/Alamy)","copyrightlink":"https://www.bing.com/search?q=Beavers+Bend+Resort+Park+Oklahoma&form=hpcapt&filters=HpDate%3a%2220211112_0800%22","title":"A vivid scene from Beavers Bend","quiz":"/search?q=Bing+homepage+quiz&filters=WQOskey:%22HPQuiz_20211112_BeaversBend%22&FORM=HPQUIZ","wp":true,"hsh":"1ef0d2990ec72697766bb83e615cb1dd","drk":1,"top":1,"bot":1,"hs":[]},{"startdate":"20211111","fullstartdate":"202111110800","enddate":"20211112","url":"/th?id=OHR.Veterans2021_EN-US8913164564_1920x1080.jpg&rf=LaDigue_1920x1080.jpg&pid=hp","urlbase":"/th?id=OHR.Veterans2021_EN-US8913164564","copyright":"Service members on the amphibious assault ship USS Iwo Jima on New York's Hudson River during Veterans Week, 2016 (© Apple White/Alamy)","copyrightlink":"https://www.bing.com/search?q=veterans+day&form=hpcapt&filters=HpDate%3a%2220211111_0800%22","title":"Honoring our veterans","quiz":"/search?q=Bing+homepage+quiz&filters=WQOskey:%22HPQuiz_20211111_Veterans2021%22&FORM=HPQUIZ","wp":true,"hsh":"2e39468c76bea58d18c5bdc7c16c6c8f","drk":1,"top":1,"bot":1,"hs":[]},{"startdate":"20211110","fullstartdate":"202111100800","enddate":"20211111","url":"/th?id=OHR.CumberlandSeashore_EN-US8862017440_1920x1080.jpg&rf=LaDigue_1920x1080.jpg&pid=hp","urlbase":"/th?id=OHR.CumberlandSeashore_EN-US8862017440","copyright":"Cumberland Island National Seashore, Georgia (© Wilsilver77/Getty Images Plus)","copyrightlink":"https://www.bing.com/search?q=Cumberland+Island+National+Seashore&FORM=hpcapt&filters=HpDate%3a%2220211110_0800%22","title":"An island 'where nature and history meet'","quiz":"/search?q=Bing+homepage+quiz&filters=WQOskey:%22HPQuiz_20211110_CumberlandSeashore%22&FORM=HPQUIZ","wp":true,"hsh":"643ec762a0908080ecb8101744f9cf0f","drk":1,"top":1,"bot":1,"hs":[]}],"tooltips":{"loading":"Loading...","previous":"Previous image","next":"Next image","walle":"This image is not available to download as wallpaper.","walls":"Download this image. Use of this image is restricted to wallpaper only."}}